physiomodeler/__init__.py
physiomodeler/converters.py
physiomodeler/events.py
physiomodeler/physiomodel.py
physiomodeler/post_analysis.py
physiomodeler-0.5.3.dist-info/METADATA
physiomodeler-0.5.3.dist-info/WHEEL
physiomodeler-0.5.3.dist-info/licenses/LICENSE
physiomodeler-0.5.3.dist-info/RECORD
