Metadata-Version: 2.3
Name: physiomodeler
Version: 0.5.3
Summary: Create physiological models for educational purposes.
Author-email: Peter Somhorst <p.somhorst@tudelft.nl>
License: The MIT License (MIT)
Keywords: education,modelling,physiology,respiration,simulation
Classifier: License :: OSI Approved :: MIT License
Requires-Python: >=3.11
Requires-Dist: attrs
Requires-Dist: matplotlib
Requires-Dist: numpy
Requires-Dist: pandas
Requires-Dist: scipy
Provides-Extra: dev
Requires-Dist: hatchling>=1.26.1; extra == 'dev'
Provides-Extra: docs
Requires-Dist: black; extra == 'docs'
Requires-Dist: mike; extra == 'docs'
Requires-Dist: mkdocs; extra == 'docs'
Requires-Dist: mkdocs-exclude; extra == 'docs'
Requires-Dist: mkdocs-material; extra == 'docs'
Requires-Dist: mkdocstrings; extra == 'docs'
Requires-Dist: mkdocstrings-python; extra == 'docs'
Requires-Dist: pymdown-extensions; extra == 'docs'
